LICENSE
README.md
setup.cfg
setup.py
bin/neucli
neucli/__init__.py
neucli/aws.py
neucli/installer.py
neucli/lib.py
neucli/version.py
neucli.egg-info/PKG-INFO
neucli.egg-info/SOURCES.txt
neucli.egg-info/dependency_links.txt
neucli.egg-info/not-zip-safe
neucli.egg-info/top_level.txt