Metadata-Version: 2.1
Name: neucli
Version: 0.3.3
Summary: Neulabs cli
Home-page: https://github.com/neulabscom/neulabs-cli
Author: Neulabs
Author-email: tech@neulabs.com
License: Apache 2.0
Platform: UNKNOWN
Classifier: Programming Language :: Python
Classifier: Programming Language :: Python :: 3
Classifier: Programming Language :: Python :: 3.7
Classifier: Programming Language :: Python :: 3.8
Classifier: Programming Language :: Python :: 3.9
Classifier: Programming Language :: Python :: 3.10
Classifier: Programming Language :: Python :: 3.11
Classifier: Operating System :: OS Independent
Requires-Python: >=3.8
